ihcmqtt/__init__.py
ihcmqtt/gateway.py
ihcmqtt_gateway-1.0.1.dist-info/METADATA
ihcmqtt_gateway-1.0.1.dist-info/WHEEL
ihcmqtt_gateway-1.0.1.dist-info/entry_points.txt
ihcmqtt_gateway-1.0.1.dist-info/top_level.txt
ihcmqtt_gateway-1.0.1.dist-info/RECORD
