Metadata-Version: 2.1
Name: ihcmqtt-gateway
Version: 1.0.1
Summary: IHC-MQTT gateway
Home-page: https://github.com/jakobdalsgaard/ihcmqtt
Author: Jakob Dalsgaard
Author-email: jakob@dalsgaard.net
License: MIT
Platform: UNKNOWN
Classifier: License :: OSI Approved :: MIT License
Classifier: Programming Language :: Python :: 3
Classifier: Programming Language :: Python :: 3.7
Requires-Dist: ihcsdk
Requires-Dist: paho-mqtt
